Source/__init__.py
devtoolkit-0.2.2.dist-info/METADATA
devtoolkit-0.2.2.dist-info/WHEEL
devtoolkit-0.2.2.dist-info/top_level.txt
devtoolkit-0.2.2.dist-info/RECORD
