Metadata-Version: 2.1
Name: devtoolkit
Version: 0.2.2
Summary: System
Author: Hunter Mikesell
Author-email: huntermikesell84@gmail.com
Classifier: Programming Language :: Python :: 3
Classifier: License :: OSI Approved :: MIT License
Classifier: Operating System :: OS Independent
